icbc/__init__.py
icbc/easygui.py
icbc/icon_config.ico
icbc/icon_icbc.ico
icbc/icon_sync.ico
icbc/socks.py
icbc/ssdp.py
icbc/z.py
icbc/zen_app.py
icbc/zen_con.py
icbc/zen_gui.py
icbc/zen_ie.py
icbc/zen_key.py
icbc/zen_net.py
icbc/zen_thread_pool.py
icbc/zen_tool.py
icbc/zen_tool_unittest.py
icbc/zen_tp.py
icbc-2.1.2.dist-info/License.txt
icbc-2.1.2.dist-info/METADATA
icbc-2.1.2.dist-info/WHEEL
icbc-2.1.2.dist-info/top_level.txt
icbc-2.1.2.dist-info/RECORD
