Metadata-Version: 2.1
Name: icbc
Version: 2.1.2
Summary: personal utilities code
Author: lhyweb
Author-email: lhyweb@gmail.com
Keywords: icbc,tool,gui,ie,mouse
Classifier: Programming Language :: Python :: 3
Classifier: License :: OSI Approved :: MIT License
Classifier: Operating System :: OS Independent
License-File: License.txt
